README.rst
setup.cfg
setup.py
md_environ/__init__.py
md_environ/environ.py
md_environ.egg-info/PKG-INFO
md_environ.egg-info/SOURCES.txt
md_environ.egg-info/dependency_links.txt
md_environ.egg-info/requires.txt
md_environ.egg-info/top_level.txt